progressbar_simple-0.1.dist-info/DESCRIPTION.rst
progressbar_simple-0.1.dist-info/METADATA
progressbar_simple-0.1.dist-info/RECORD
progressbar_simple-0.1.dist-info/WHEEL
progressbar_simple-0.1.dist-info/metadata.json
progressbar_simple-0.1.dist-info/top_level.txt
progressbarsimple/__init__.py
