Metadata-Version: 2.0
Name: progressbar-simple
Version: 0.1
Summary: Another simple progress bar
Home-page: http://github.com/vgeck/progressBar
Author: Vinzenz Eck
Author-email: vinzenz@xal.no
License: GNU3
Keywords: terminal process bar
Platform: UNKNOWN
Classifier: Development Status :: 4 - Beta
Classifier: Intended Audience :: Developers
Classifier: License :: OSI Approved :: GNU General Public License v3 (GPLv3)
Classifier: Natural Language :: English
Classifier: Programming Language :: Python :: 2.7
Classifier: Programming Language :: Python :: 3.5
Classifier: Topic :: Utilities
Requires-Dist: future
